kidash/__init__.py
kidash/_version.py
kidash/bin/kidash.py
kidash/kidash.py
kidash-1.1.6.dist-info/METADATA
kidash-1.1.6.dist-info/WHEEL
kidash-1.1.6.dist-info/entry_points.txt
kidash-1.1.6.dist-info/licenses/AUTHORS
kidash-1.1.6.dist-info/licenses/LICENSE
kidash-1.1.6.dist-info/RECORD
